zipexec/__main__.py
zipexec-1.0.dist-info/LICENSE
zipexec-1.0.dist-info/METADATA
zipexec-1.0.dist-info/WHEEL
zipexec-1.0.dist-info/entry_points.txt
zipexec-1.0.dist-info/top_level.txt
zipexec-1.0.dist-info/RECORD
