Metadata-Version: 2.1
Name: zipexec
Version: 1.0
Summary: Unzip zip files and run commands against the contents
Home-page: http://github.com/markbaggett/zipexec
Author-email: lo127001@gmail.com
License: GNU Lesser General Public License v3 (LGPLv3)
Platform: UNKNOWN
Classifier: Programming Language :: Python :: 3
Classifier: License :: OSI Approved :: GNU Lesser General Public License v3 (LGPLv3)
Classifier: Operating System :: OS Independent
